[
    {
        "2021":[
            {
                "weltmeisterschaft_freistil":{
                    "actualTeilnehmer":"",
                    "actualTeilnehmerGk":"",
                    "gewichtsklassen":[
                        {
                            "gewicht":61,
                            "teilnehmer":[]
                        },
                        {
                            "gewicht":65,
                            "teilnehmer":[]
                        },
                        {
                            "gewicht":70,
                            "teilnehmer":[]
                        },
                        {
                            "gewicht":79,
                            "teilnehmer":[]
                        },
                        {
                            "gewicht":96,
                            "teilnehmer":[]
                        },
                        {
                            "gewicht":130,
                            "teilnehmer":[]
                        }
                    ],
                    "kampfhistorie":[
                        {
                            "gewichtsklasse":"",
                            "kampfID":"",
                            "punkteBlau":"",
                            "punkteRot":"",
                            "runde":"",
                            "sieger":"",
                            "siegesart":""
                        }
                    ],
                    "kampfstil":"freistil",
                    "rangliste":[
                        {
                            "61":[
                                {
                                    "land":"",
                                    "nachname":"",
                                    "rang":1,
                                    "vorname":""
                                }
                            ]
                        }
                    ],
                    "teilnehmerGrenze":"48",
                    "teilnehmerGrenzeGk":"8"
                }
            }
        ]
    }
]